fhir.profiling-0.0.1-py3.8-nspkg.pth
fhir/profiling/__init__.py
fhir/profiling/py.typed
fhir/profiling/parser/__init__.py
fhir/profiling/parser/listeners.py
fhir/profiling/parser/node.py
fhir/profiling/parser/evaluators/__init__.py
fhir/profiling/parser/evaluators/api.py
fhir/profiling/parser/evaluators/base.py
fhir/profiling/parser/evaluators/expression.py
fhir/profiling/parser/evaluators/invocation.py
fhir/profiling/parser/fhirpath_grammar/FHIRPathExpression.g4
fhir/profiling/parser/fhirpath_grammar/FHIRPathExpression.interp
fhir/profiling/parser/fhirpath_grammar/FHIRPathExpression.tokens
fhir/profiling/parser/fhirpath_grammar/FHIRPathExpressionLexer.interp
fhir/profiling/parser/fhirpath_grammar/FHIRPathExpressionLexer.py
fhir/profiling/parser/fhirpath_grammar/FHIRPathExpressionLexer.tokens
fhir/profiling/parser/fhirpath_grammar/FHIRPathExpressionListener.py
fhir/profiling/parser/fhirpath_grammar/FHIRPathExpressionParser.py
fhir/profiling/parser/fhirpath_grammar/__init__.py
fhir.profiling-0.0.1.dist-info/AUTHORS.rst
fhir.profiling-0.0.1.dist-info/LICENSE
fhir.profiling-0.0.1.dist-info/METADATA
fhir.profiling-0.0.1.dist-info/WHEEL
fhir.profiling-0.0.1.dist-info/namespace_packages.txt
fhir.profiling-0.0.1.dist-info/top_level.txt
fhir.profiling-0.0.1.dist-info/RECORD
