Metadata-Version: 2.1
Name: fhir.profiling
Version: 0.0.1
Summary: FHIR profile validator.
Home-page: https://github.com/nazrulworld/fhir.profiling
Author: Md Nazrul Islam
Author-email: email2nazrul@gmail.com
License: BSD license
Project-URL: CI: Travis, https://travis-ci.org/github/nazrulworld/fhir.profiling
Project-URL: Coverage: codecov, https://codecov.io/gh/nazrulworld/fhir.profiling
Project-URL: GitHub: issues, https://github.com/nazrulworld/fhir.profiling/issues
Project-URL: GitHub: repo, https://github.com/nazrulworld/fhir.profiling
Keywords: fhir,profiling,python,hl7,health IT,healthcare
Classifier: Development Status :: 3 - Alpha
Classifier: Intended Audience :: Developers
Classifier: License :: OSI Approved :: BSD License
Classifier: Natural Language :: English
Classifier: Programming Language :: Python :: 3
Classifier: Programming Language :: Python :: 3 :: Only
Classifier: Programming Language :: Python :: 3.6
Classifier: Programming Language :: Python :: 3.7
Classifier: Programming Language :: Python :: 3.8
Classifier: Programming Language :: Python :: 3.9
Classifier: Intended Audience :: Developers
Classifier: Intended Audience :: Education
Classifier: Intended Audience :: Healthcare Industry
Classifier: Intended Audience :: Information Technology
Classifier: Intended Audience :: Science/Research
Classifier: Operating System :: OS Independent
Classifier: Typing :: Typed
Requires-Python: >=3.6
License-File: LICENSE
License-File: AUTHORS.rst
Requires-Dist: antlr4-python3-runtime (==4.9.3)
Requires-Dist: pydantic (>=1.7.2)
Provides-Extra: dev
Requires-Dist: fhir.resources ; extra == 'dev'
Requires-Dist: coverage ; extra == 'dev'
Requires-Dist: flake8 (==3.8.3) ; extra == 'dev'
Requires-Dist: flake8-isort (==3.0.0) ; extra == 'dev'
Requires-Dist: flake8-bugbear (==20.1.4) ; extra == 'dev'
Requires-Dist: isort (==4.3.21) ; extra == 'dev'
Requires-Dist: black ; extra == 'dev'
Requires-Dist: mypy (==0.812) ; extra == 'dev'
Requires-Dist: Jinja2 (==2.11.1) ; extra == 'dev'
Requires-Dist: MarkupSafe (==1.1.1) ; extra == 'dev'
Requires-Dist: colorlog (==2.10.0) ; extra == 'dev'
Requires-Dist: certifi ; extra == 'dev'
Requires-Dist: zest-releaser[recommended] ; extra == 'dev'
Requires-Dist: pytest-runner ; extra == 'dev'
Requires-Dist: pytest (>5.4.0) ; (python_version >= "3.6") and extra == 'dev'
Requires-Dist: pytest-cov (>=2.10.0) ; (python_version >= "3.6") and extra == 'dev'
Provides-Extra: test
Requires-Dist: fhir.resources ; extra == 'test'
Requires-Dist: coverage ; extra == 'test'
Requires-Dist: flake8 (==3.8.3) ; extra == 'test'
Requires-Dist: flake8-isort (==3.0.0) ; extra == 'test'
Requires-Dist: flake8-bugbear (==20.1.4) ; extra == 'test'
Requires-Dist: isort (==4.3.21) ; extra == 'test'
Requires-Dist: black ; extra == 'test'
Requires-Dist: mypy (==0.812) ; extra == 'test'
Requires-Dist: pytest-runner ; extra == 'test'
Requires-Dist: pytest (>5.4.0) ; (python_version >= "3.6") and extra == 'test'
Requires-Dist: pytest-cov (>=2.10.0) ; (python_version >= "3.6") and extra == 'test'
